.project
.pydevproject
__init__.py
cernent.py
cernentd.py
ez_setup.py
rftest.py
setup.py
Cernent.egg-info/PKG-INFO
Cernent.egg-info/SOURCES.txt
Cernent.egg-info/dependency_links.txt
Cernent.egg-info/entry_points.txt
Cernent.egg-info/requires.txt
Cernent.egg-info/top_level.txt
NessusCom/NessusCommunicator.py
NessusCom/__init__.py
ReportFramework/RFReportProcs.py
ReportFramework/RFTargetProcs.py
ReportFramework/RFVulnProcs.py
ReportFramework/ReportFramework.py
ReportFramework/ReportManager.py
ReportFramework/__init__.py
ScanEvent/InitMode.py
ScanEvent/MarkerFileIO.py
ScanEvent/ScanEvent.py
ScanEvent/ScanRunner.py
ScanEvent/__init__.py
ScanEvent/testBatchMode.py
ScanEvent/scanEvents/DCheeTest.se
ScanEvent/scanEvents/Example Scan.se
Scheduler/Schedule_Alfonso.py
Scheduler/__init__.py
config/__init__.py
config/config.py
deliveryMethod/Mailer.py
deliveryMethod/__init__.py
doc/build/.buildinfo
doc/build/code.html
doc/build/genindex.html
doc/build/index.html
doc/build/objects.inv
doc/build/py-modindex.html
doc/build/search.html
doc/build/searchindex.js
doc/build/.doctrees/code.doctree
doc/build/.doctrees/environment.pickle
doc/build/.doctrees/index.doctree
doc/build/_sources/code.txt
doc/build/_sources/index.txt
doc/build/_static/ajax-loader.gif
doc/build/_static/basic.css
doc/build/_static/comment-bright.png
doc/build/_static/comment-close.png
doc/build/_static/comment.png
doc/build/_static/default.css
doc/build/_static/doctools.js
doc/build/_static/down-pressed.png
doc/build/_static/down.png
doc/build/_static/file.png
doc/build/_static/jquery.js
doc/build/_static/minus.png
doc/build/_static/plus.png
doc/build/_static/pygments.css
doc/build/_static/searchtools.js
doc/build/_static/sidebar.js
doc/build/_static/underscore.js
doc/build/_static/up-pressed.png
doc/build/_static/up.png
doc/build/_static/websupport.js
doc/source/code.rst
doc/source/conf.py
doc/source/index.rst
etc/__init__.py
etc/cernent.conf
etc/gui.cfg
gui/__init__.py
gui/cGui/__init__.py
gui/cGui/config/GuiConfig.py
gui/cGui/config/__init__.py
gui/cGui/controller/CGuiController.py
gui/cGui/controller/__init__.py
gui/cGui/main/Launchpad.py
gui/cGui/main/ReportsView.py
