Metadata-Version: 1.0
Name: Cernent
Version: 0.1.0
Summary: Vulnerability Reporter
Home-page: UNKNOWN
Author: CernentTeam
Author-email: CernentTeam@gmail.com
License: UNKNOWN
Platform: UNKNOWN
